leximited/__init__.py
leximited/leximited.py
leximited-1.1.1.dist-info/LICENSE
leximited-1.1.1.dist-info/METADATA
leximited-1.1.1.dist-info/WHEEL
leximited-1.1.1.dist-info/top_level.txt
leximited-1.1.1.dist-info/RECORD
