Metadata-Version: 2.1
Name: leximited
Version: 1.1.1
Summary: Lexicographically Delimited Encoding
Home-page: https://github.com/isaac-art/py-leximited
Author: Isaac Clarke
Author-email: isaac@isaacclarke.com
License: UNKNOWN
Platform: UNKNOWN
Classifier: Programming Language :: Python :: 3
Classifier: License :: OSI Approved :: GNU General Public License v3 (GPLv3)
Classifier: Operating System :: OS Independent
Requires-Python: >=3.6
